plot_map/__init__.py
plot_map/plot_map.py
plot_map-0.3.6.dist-info/LICENSE
plot_map-0.3.6.dist-info/METADATA
plot_map-0.3.6.dist-info/WHEEL
plot_map-0.3.6.dist-info/top_level.txt
plot_map-0.3.6.dist-info/RECORD
