Metadata-Version: 2.1
Name: plot-map
Version: 0.3.6
Summary: A tool to add basemap in matplotlib
Home-page: https://github.com/ni1o1/plot_map
Author: Qing Yu
Author-email: qingyu0815@foxmail.com
License: MIT
Project-URL: Bug Tracker, https://github.com/ni1o1/plot_map/issues
Platform: UNKNOWN
Classifier: Environment :: Web Environment
Classifier: Intended Audience :: Developers
Classifier: Operating System :: OS Independent
Classifier: Framework :: Matplotlib
Classifier: Topic :: Text Processing :: Indexing
Classifier: Topic :: Utilities
Classifier: Topic :: Internet
Classifier: Topic :: Software Development :: Libraries :: Python Modules
Classifier: Programming Language :: Python
Classifier: Programming Language :: Python :: 3.8
Requires-Python: >=3.6
License-File: LICENSE
Requires-Dist: geopandas
Requires-Dist: matplotlib
